docgetter/__init__.py
docgetter/main.py
docgetter/parser.py
lib/docgetter/__init__.py
lib/docgetter/main.py
lib/docgetter/parser.py
docgetter-0.1.2.dist-info/LICENSE
docgetter-0.1.2.dist-info/METADATA
docgetter-0.1.2.dist-info/WHEEL
docgetter-0.1.2.dist-info/entry_points.txt
docgetter-0.1.2.dist-info/top_level.txt
docgetter-0.1.2.dist-info/RECORD
