Metadata-Version: 2.1
Name: docgetter
Version: 0.1.2
Summary: Command line shortcut for opening Python documentation
Home-page: https://github.com/vinlin24/docgetter
Author: Vincent Lin
Author-email: vinlin24@outlook.com
License: MIT
Project-URL: Bug Tracker, https://github.com/vinlin24/docgetter/issues
Platform: UNKNOWN
Classifier: Programming Language :: Python :: 3
Requires-Python: >=3.7
